cmo_dataexplore/__init__.py
cmo_dataexplore/explore.py
cmo_dataexplore/resources.py
cmo_dataexplore/data/example.csv
cmo_dataexplore/notebooks/Cmotions DataExplore tutorial.ipynb
cmo_dataexplore-0.0.1.dist-info/METADATA
cmo_dataexplore-0.0.1.dist-info/WHEEL
cmo_dataexplore-0.0.1.dist-info/top_level.txt
cmo_dataexplore-0.0.1.dist-info/RECORD
