Metadata-Version: 2.1
Name: cmo-dataexplore
Version: 0.0.1
Summary: Basic data exploration, fast and easy
Home-page: https://dev.azure.com/Cmotions/Packages/_git/cmo_dataexplore
Author: Jeanine Schoonemann
Author-email: service@cmotions.nl
Requires-Python: >=3.6
Requires-Dist: scikit-learn (>=0.20.2)
Requires-Dist: ppscore (>=1.2.0)
Requires-Dist: cmo-dataviz
Provides-Extra: dev
Requires-Dist: black ; extra == 'dev'
Requires-Dist: jupyterlab ; extra == 'dev'
Requires-Dist: pytest (>=6.2.4) ; extra == 'dev'
Requires-Dist: ipykernel ; extra == 'dev'
Requires-Dist: twine ; extra == 'dev'
